pygats/__init__.py
pygats/formatters.py
pygats/misc.py
pygats/pygats.py
pygats/qat.py
pygats/recog.py
pygats-0.2.0.dist-info/LICENSE
pygats-0.2.0.dist-info/METADATA
pygats-0.2.0.dist-info/WHEEL
pygats-0.2.0.dist-info/top_level.txt
pygats-0.2.0.dist-info/RECORD
