Metadata-Version: 2.2
Name: pyGATs
Version: 0.2.0
Summary: Automate end-to-end and exploratory testing
Author: vsysoev
License: MIT License
Project-URL: repository, https://github.com/IntegraSDL/pymagic-autogui.git
Keywords: gui,testing,automatic
Classifier: Programming Language :: Python :: 3
Classifier: License :: OSI Approved :: MIT License
Requires-Python: >=3.9
License-File: LICENSE
Requires-Dist: pyautogui
Requires-Dist: Pillow
Requires-Dist: pytesseract
Requires-Dist: Levenshtein
Requires-Dist: opencv-python
Requires-Dist: numpy
Requires-Dist: colorama
Requires-Dist: mss
Requires-Dist: hdbscan
Provides-Extra: test
Requires-Dist: pytest>5.0.0; extra == "test"
